{
	"info": {
		"_postman_id": "f0107ffe-f56e-43a5-9900-d458bef2b5dc",
		"name": "04 Seller CRUD",
		"schema": "https://schema.getpostman.com/json/collection/v2.1.0/collection.json",
		"_exporter_id": "21558482"
	},
	"item": [
		{
			"name": "GetById",
			"request": {
				"method": "GET",
				"header": [],
				"url": {
					"raw": "http://localhost:8080/api/v1/fresh-products/seller/1",
					"protocol": "http",
					"host": [
						"localhost"
					],
					"port": "8080",
					"path": [
						"api",
						"v1",
						"fresh-products",
						"seller",
						"1"
					]
				}
			},
			"response": []
		},
		{
			"name": "Insert",
			"request": {
				"method": "POST",
				"header": [],
				"body": {
					"mode": "raw",
					"raw": "{\n    \"name\": \"Ricardo Teste\"\n}",
					"options": {
						"raw": {
							"language": "json"
						}
					}
				},
				"url": {
					"raw": "http://localhost:8080/api/v1/fresh-products/seller",
					"protocol": "http",
					"host": [
						"localhost"
					],
					"port": "8080",
					"path": [
						"api",
						"v1",
						"fresh-products",
						"seller"
					]
				}
			},
			"response": []
		},
		{
			"name": "Update",
			"request": {
				"method": "PUT",
				"header": [],
				"body": {
					"mode": "raw",
					"raw": "{\n    \"id\": 1,\n    \"name\": \"Ricardo Teste 2.0\"\n}",
					"options": {
						"raw": {
							"language": "json"
						}
					}
				},
				"url": {
					"raw": "http://localhost:8080/api/v1/fresh-products/seller",
					"protocol": "http",
					"host": [
						"localhost"
					],
					"port": "8080",
					"path": [
						"api",
						"v1",
						"fresh-products",
						"seller"
					]
				}
			},
			"response": []
		},
		{
			"name": "Delete",
			"request": {
				"method": "DELETE",
				"header": [],
				"url": {
					"raw": "http://localhost:8080/api/v1/fresh-products/seller/1",
					"protocol": "http",
					"host": [
						"localhost"
					],
					"port": "8080",
					"path": [
						"api",
						"v1",
						"fresh-products",
						"seller",
						"1"
					]
				}
			},
			"response": []
		}
	]
}